user_visit/__init__.py
user_visit/admin.py
user_visit/apps.py
user_visit/middleware.py
user_visit/migrations/0001_initial.py
user_visit/migrations/0002_add_created_at.py
user_visit/migrations/__init__.py
user_visit/models.py
user_visit/settings.py
django_user_visit-0.3.3.dist-info/LICENSE
django_user_visit-0.3.3.dist-info/WHEEL
django_user_visit-0.3.3.dist-info/METADATA
django_user_visit-0.3.3.dist-info/RECORD
